LianaiJiaokeshu/README.md
LianaiJiaokeshu/__init__.py
LianaiJiaokeshu/__main__.py
LianaiJiaokeshu/file.epub
LianaiJiaokeshu/index.html
LianaiJiaokeshu/css/__init__.py
LianaiJiaokeshu/css/annotations.css
LianaiJiaokeshu/css/main.css
LianaiJiaokeshu/css/normalize.css
LianaiJiaokeshu/css/popup.css
LianaiJiaokeshu/font/__init__.py
LianaiJiaokeshu/font/fontello.eot
LianaiJiaokeshu/font/fontello.svg
LianaiJiaokeshu/font/fontello.ttf
LianaiJiaokeshu/font/fontello.woff
LianaiJiaokeshu/img/__init__.py
LianaiJiaokeshu/img/annotator-glyph-sprite.png
LianaiJiaokeshu/img/annotator-icon-sprite.png
LianaiJiaokeshu/img/apple-touch-icon.png
LianaiJiaokeshu/img/cancelfullscreen.png
LianaiJiaokeshu/img/close.png
LianaiJiaokeshu/img/fullscreen.png
LianaiJiaokeshu/img/loader.gif
LianaiJiaokeshu/img/menu-icon.png
LianaiJiaokeshu/img/save.png
LianaiJiaokeshu/img/saved.png
LianaiJiaokeshu/img/settings-s.png
LianaiJiaokeshu/img/settings.png
LianaiJiaokeshu/img/star.png
LianaiJiaokeshu/js/__init__.py
LianaiJiaokeshu/js/epub.js
LianaiJiaokeshu/js/epub.min.js
LianaiJiaokeshu/js/epub.min.map
LianaiJiaokeshu/js/hooks.min.js
LianaiJiaokeshu/js/hooks.min.map
LianaiJiaokeshu/js/reader.js
LianaiJiaokeshu/js/reader.js.map
LianaiJiaokeshu/js/reader.min.js
LianaiJiaokeshu/js/reader.min.map
LianaiJiaokeshu/js/hooks/__init__.py
LianaiJiaokeshu/js/hooks/extensions/__init__.py
LianaiJiaokeshu/js/hooks/extensions/highlight.js
LianaiJiaokeshu/js/libs/__init__.py
LianaiJiaokeshu/js/libs/jquery.min.js
LianaiJiaokeshu/js/libs/localforage.min.js
LianaiJiaokeshu/js/libs/screenfull.js
LianaiJiaokeshu/js/libs/screenfull.min.js
LianaiJiaokeshu/js/libs/zip.min.js
LianaiJiaokeshu/js/plugins/__init__.py
LianaiJiaokeshu/js/plugins/hypothesis.js
LianaiJiaokeshu/js/plugins/search.js
lianai_jiaokeshu-2022.10.11.0.dist-info/METADATA
lianai_jiaokeshu-2022.10.11.0.dist-info/WHEEL
lianai_jiaokeshu-2022.10.11.0.dist-info/entry_points.txt
lianai_jiaokeshu-2022.10.11.0.dist-info/top_level.txt
lianai_jiaokeshu-2022.10.11.0.dist-info/RECORD
